<odoo>

  <record id="vsao_res_partner_form" model="ir.ui.view">
    <field name="name">vsao.res.partner.inherit</field>
    <field name="model">res.partner</field>
    <field name="inherit_id" ref="base.view_partner_form"/>
    <field name="arch" type="xml">
      <xpath expr="//group/group/field[@name='category_id']" position="after">
        <field name="vsao_POS_available"/>
      </xpath>
    </field>
  </record>
  <record id="view_partner_pos_kanban" model="ir.ui.view">
      <field name="name">res.partner.pos.kanban.inherit</field>
      <field name="model">res.partner</field>
      <field name="inherit_id" ref="base.res_partner_kanban_view"/>
      <field name="context" eval="{'vsao_POS_filter_Partner': True}"/>
      </field>
  </record>
</odoo>